bigchaindb_common/__init__.py
bigchaindb_common/crypto.py
bigchaindb_common/exceptions.py
bigchaindb_common/transaction.py
bigchaindb_common/util.py
bigchaindb_common-0.0.2.dev1.dist-info/DESCRIPTION.rst
bigchaindb_common-0.0.2.dev1.dist-info/METADATA
bigchaindb_common-0.0.2.dev1.dist-info/RECORD
bigchaindb_common-0.0.2.dev1.dist-info/WHEEL
bigchaindb_common-0.0.2.dev1.dist-info/metadata.json
bigchaindb_common-0.0.2.dev1.dist-info/top_level.txt
